{
  "video_name": "video_017.mp4",
  "total_frames": 20,
  "duration_seconds": 20.0,
  "summary": {
    "total_people": 2,
    "people_types": [
      "adult",
      "baby",
      "child"
    ]
  },
  "frames": [
    {
      "frame": 0,
      "timestamp": 0.0,
      "people": [],
      "objects_rekognition": [
        "Head",
        "Person",
        "Face",
        "Indoors",
        "Interior Design",
        "Happy"
      ]
    },
    {
      "frame": 1,
      "timestamp": 1.0,
      "people": [
        {
          "type": "baby",
          "age": 1,
          "age_range": "0-2",
          "gender": "female",
          "emotion": "neutral"
        }
      ],
      "objects_rekognition": [
        "Head",
        "Person",
        "Face",
        "Happy",
        "Baby",
        "Baby Laughing",
        "Box",
        "Package"
      ]
    },
    {
      "frame": 2,
      "timestamp": 2.0,
      "people": [
        {
          "type": "baby",
          "age": 1,
          "age_range": "0-2",
          "gender": "female",
          "emotion": "neutral"
        },
        {
          "type": "adult",
          "age": 35,
          "age_range": "30-40",
          "gender": "female",
          "emotion": "happy"
        }
      ],
      "objects_rekognition": [
        "Head",
        "Person",
        "Face",
        "Happy"
      ]
    },
    {
      "frame": 3,
      "timestamp": 3.0,
      "people": [
        {
          "type": "baby",
          "age": 1,
          "age_range": "0-2",
          "gender": "unknown",
          "emotion": "neutral"
        }
      ],
      "objects_rekognition": [
        "Head",
        "Person",
        "Face",
        "Happy",
        "Baby",
        "Baby Laughing"
      ]
    },
    {
      "frame": 4,
      "timestamp": 4.0,
      "people": [
        {
          "type": "baby",
          "age": 1,
          "age_range": "0-2",
          "gender": "female",
          "emotion": "neutral"
        },
        {
          "type": "adult",
          "age": 30,
          "age_range": "25-35",
          "gender": "female",
          "emotion": "neutral"
        }
      ],
      "objects_rekognition": [
        "Face",
        "Head",
        "Person"
      ]
    },
    {
      "frame": 5,
      "timestamp": 5.0,
      "people": [
        {
          "type": "adult",
          "age": 30,
          "age_range": "25-35",
          "gender": "female",
          "emotion": "happy"
        },
        {
          "type": "baby",
          "age": 2,
          "age_range": "0-2",
          "gender": "female",
          "emotion": "neutral"
        }
      ],
      "objects_rekognition": [
        "Head",
        "Person",
        "Face",
        "Happy",
        "Smile"
      ]
    },
    {
      "frame": 6,
      "timestamp": 6.0,
      "people": [
        {
          "type": "baby",
          "age": 1,
          "age_range": "0-2",
          "gender": "female",
          "emotion": "neutral"
        },
        {
          "type": "adult",
          "age": 30,
          "age_range": "25-35",
          "gender": "female",
          "emotion": "happy"
        }
      ],
      "objects_rekognition": [
        "Face",
        "Head",
        "Person"
      ]
    },
    {
      "frame": 7,
      "timestamp": 7.0,
      "people": [
        {
          "type": "baby",
          "age": 1,
          "age_range": "0-2",
          "gender": "unknown",
          "emotion": "neutral"
        },
        {
          "type": "adult",
          "age": 30,
          "age_range": "25-35",
          "gender": "female",
          "emotion": "happy"
        }
      ],
      "objects_rekognition": [
        "Face",
        "Head",
        "Person",
        "Happy",
        "Baby",
        "Baby Laughing",
        "Animal",
        "Cat",
        "Mammal",
        "Pet"
      ]
    },
    {
      "frame": 8,
      "timestamp": 8.0,
      "people": [
        {
          "type": "baby",
          "age": 1,
          "age_range": "0-2",
          "gender": "unknown",
          "emotion": "neutral"
        },
        {
          "type": "adult",
          "age": 30,
          "age_range": "25-35",
          "gender": "female",
          "emotion": "calm"
        }
      ],
      "objects_rekognition": [
        "Crawling",
        "Person",
        "Animal",
        "Cat",
        "Mammal",
        "Pet"
      ]
    },
    {
      "frame": 9,
      "timestamp": 9.0,
      "people": [
        {
          "type": "baby",
          "age": 1,
          "age_range": "0-2",
          "gender": "unknown",
          "emotion": "excited"
        },
        {
          "type": "adult",
          "age": 30,
          "age_range": "25-35",
          "gender": "female",
          "emotion": "happy"
        }
      ],
      "objects_rekognition": [
        "Head",
        "Person",
        "Face",
        "Happy",
        "Child",
        "Female",
        "Girl",
        "Baby",
        "Baby Laughing"
      ]
    },
    {
      "frame": 10,
      "timestamp": 10.0,
      "people": [
        {
          "type": "baby",
          "age": 1,
          "age_range": "0-2",
          "gender": "unknown",
          "emotion": "neutral"
        }
      ],
      "objects_rekognition": [
        "Face",
        "Head",
        "Person",
        "Happy"
      ]
    },
    {
      "frame": 11,
      "timestamp": 11.0,
      "people": [
        {
          "type": "baby",
          "age": 1,
          "age_range": "0-2",
          "gender": "female",
          "emotion": "neutral"
        },
        {
          "type": "adult",
          "age": 30,
          "age_range": "25-35",
          "gender": "female",
          "emotion": "happy"
        }
      ],
      "objects_rekognition": [
        "Head",
        "Person",
        "Face",
        "Happy",
        "Baby",
        "Baby Laughing"
      ]
    },
    {
      "frame": 12,
      "timestamp": 12.0,
      "people": [
        {
          "type": "baby",
          "age": 1,
          "age_range": "0-2",
          "gender": "female",
          "emotion": "neutral"
        },
        {
          "type": "adult",
          "age": 30,
          "age_range": "25-35",
          "gender": "female",
          "emotion": "happy"
        }
      ],
      "objects_rekognition": [
        "Face",
        "Head",
        "Person",
        "Happy"
      ]
    },
    {
      "frame": 13,
      "timestamp": 13.0,
      "people": [
        {
          "type": "baby",
          "age": 1,
          "age_range": "0-2",
          "gender": "female",
          "emotion": "neutral"
        },
        {
          "type": "adult",
          "age": 30,
          "age_range": "25-35",
          "gender": "female",
          "emotion": "calm"
        }
      ],
      "objects_rekognition": [
        "Face",
        "Head",
        "Person"
      ]
    },
    {
      "frame": 14,
      "timestamp": 14.0,
      "people": [
        {
          "type": "baby",
          "age": 1,
          "age_range": "0-2",
          "gender": "female",
          "emotion": "neutral"
        },
        {
          "type": "adult",
          "age": 30,
          "age_range": "25-35",
          "gender": "female",
          "emotion": "happy"
        }
      ],
      "objects_rekognition": [
        "Head",
        "Person",
        "Face",
        "Happy",
        "Baby",
        "Baby Laughing"
      ]
    },
    {
      "frame": 15,
      "timestamp": 15.0,
      "people": [
        {
          "type": "baby",
          "age": 2,
          "age_range": "0-2",
          "gender": "female",
          "emotion": "neutral"
        }
      ],
      "objects_rekognition": [
        "Head",
        "Person",
        "Face",
        "Happy",
        "Car",
        "Transportation",
        "Vehicle",
        "Can",
        "Tin",
        "Baby",
        "Baby Laughing"
      ]
    },
    {
      "frame": 16,
      "timestamp": 16.0,
      "people": [
        {
          "type": "baby",
          "age": 1,
          "age_range": "0-2",
          "gender": "female",
          "emotion": "neutral"
        },
        {
          "type": "adult",
          "age": 30,
          "age_range": "25-35",
          "gender": "female",
          "emotion": "happy"
        }
      ],
      "objects_rekognition": [
        "Crawling",
        "Person",
        "Baby",
        "Baby Crawling",
        "Face",
        "Head",
        "Child",
        "Female",
        "Girl"
      ]
    },
    {
      "frame": 17,
      "timestamp": 17.0,
      "people": [
        {
          "type": "baby",
          "age": 1,
          "age_range": "0-2",
          "gender": "unknown",
          "emotion": "neutral"
        },
        {
          "type": "adult",
          "age": 30,
          "age_range": "25-35",
          "gender": "female",
          "emotion": "happy"
        }
      ],
      "objects_rekognition": [
        "Head",
        "Person",
        "Face",
        "Crawling",
        "Baby",
        "Baby Crawling"
      ]
    },
    {
      "frame": 18,
      "timestamp": 18.0,
      "people": [
        {
          "type": "child",
          "age": 4,
          "age_range": "3-5",
          "gender": "female",
          "emotion": "neutral"
        }
      ],
      "objects_rekognition": [
        "Head",
        "Person",
        "Face",
        "Happy",
        "Baby",
        "Baby Laughing"
      ]
    },
    {
      "frame": 19,
      "timestamp": 19.0,
      "people": [
        {
          "type": "baby",
          "age": 1,
          "age_range": "0-2",
          "gender": "female",
          "emotion": "happy"
        }
      ],
      "objects_rekognition": [
        "Face",
        "Happy",
        "Head",
        "Person",
        "Baby",
        "Baby Laughing"
      ]
    }
  ]
}