{
  "video_name": "video_007.mp4",
  "total_frames": 20,
  "duration_seconds": 20.0,
  "summary": {
    "total_people": 2,
    "people_types": [
      "adult",
      "baby"
    ]
  },
  "frames": [
    {
      "frame": 0,
      "timestamp": 0.0,
      "people": [
        {
          "type": "baby",
          "age": 1,
          "age_range": "0-2",
          "gender": "unknown",
          "emotion": "neutral"
        }
      ],
      "detected_objects": [
        {
          "Name": "Person",
          "Confidence": 98.6827392578125,
          "bbox": [
            0.17587979137897491,
            0.1859111338853836,
            0.4115578532218933,
            0.6794559955596924
          ],
          "Parents": []
        },
        {
          "Name": "Person",
          "Confidence": 80.99237060546875,
          "bbox": [
            0.5634982585906982,
            0.12565864622592926,
            0.30859988927841187,
            0.7526910305023193
          ],
          "Parents": []
        },
        {
          "Name": "Baby",
          "Confidence": 98.6827392578125,
          "bbox": [
            0.17587979137897491,
            0.1859111338853836,
            0.4115578532218933,
            0.6794559955596924
          ],
          "Parents": [
            "Person"
          ]
        }
      ]
    },
    {
      "frame": 1,
      "timestamp": 1.0,
      "people": [
        {
          "type": "baby",
          "age": 1,
          "age_range": "0-2",
          "gender": "unknown",
          "emotion": "happy"
        }
      ],
      "detected_objects": [
        {
          "Name": "Person",
          "Confidence": 97.53053283691406,
          "bbox": [
            0.21131210029125214,
            0.13447687029838562,
            0.3568180203437805,
            0.6606500148773193
          ],
          "Parents": []
        },
        {
          "Name": "Person",
          "Confidence": 75.90966796875,
          "bbox": [
            0.12443667650222778,
            0.1250525414943695,
            0.17708295583724976,
            0.3482775092124939
          ],
          "Parents": []
        },
        {
          "Name": "Baby",
          "Confidence": 97.53053283691406,
          "bbox": [
            0.21131210029125214,
            0.13447687029838562,
            0.3568180203437805,
            0.6606500148773193
          ],
          "Parents": [
            "Person"
          ]
        }
      ]
    },
    {
      "frame": 2,
      "timestamp": 2.0,
      "people": [
        {
          "type": "baby",
          "age": 1,
          "age_range": "0-2",
          "gender": "unknown",
          "emotion": "neutral"
        },
        {
          "type": "adult",
          "age": 30,
          "age_range": "25-35",
          "gender": "unknown",
          "emotion": "neutral"
        }
      ],
      "detected_objects": [
        {
          "Name": "Person",
          "Confidence": 96.98960876464844,
          "bbox": [
            0.15381643176078796,
            0.12332743406295776,
            0.40432173013687134,
            0.6715684533119202
          ],
          "Parents": []
        },
        {
          "Name": "Baby",
          "Confidence": 96.98960876464844,
          "bbox": [
            0.15381643176078796,
            0.12332743406295776,
            0.40432173013687134,
            0.6715684533119202
          ],
          "Parents": [
            "Person"
          ]
        },
        {
          "Name": "Sock",
          "Confidence": 92.533203125,
          "bbox": [
            0.15425728261470795,
            0.5501910448074341,
            0.11820956319570541,
            0.18421685695648193
          ],
          "Parents": [
            "Clothing",
            "Hosiery"
          ]
        },
        {
          "Name": "Sock",
          "Confidence": 75.2354736328125,
          "bbox": [
            0.2366030514240265,
            0.6481677293777466,
            0.16684190928936005,
            0.14710108935832977
          ],
          "Parents": [
            "Clothing",
            "Hosiery"
          ]
        }
      ]
    },
    {
      "frame": 3,
      "timestamp": 3.0,
      "people": [
        {
          "type": "baby",
          "age": 1,
          "age_range": "0-2",
          "gender": "unknown",
          "emotion": "calm"
        },
        {
          "type": "adult",
          "age": 30,
          "age_range": "25-35",
          "gender": "unknown",
          "emotion": "neutral"
        }
      ],
      "detected_objects": [
        {
          "Name": "Person",
          "Confidence": 98.89974975585938,
          "bbox": [
            0.1390339434146881,
            0.12194665521383286,
            0.43088221549987793,
            0.6789807677268982
          ],
          "Parents": []
        },
        {
          "Name": "Baby",
          "Confidence": 98.89974975585938,
          "bbox": [
            0.1390339434146881,
            0.12194665521383286,
            0.43088221549987793,
            0.6789807677268982
          ],
          "Parents": [
            "Person"
          ]
        }
      ]
    },
    {
      "frame": 4,
      "timestamp": 4.0,
      "people": [],
      "detected_objects": [
        {
          "Name": "Person",
          "Confidence": 97.53484344482422,
          "bbox": [
            0.12484141439199448,
            0.12123048305511475,
            0.4460567831993103,
            0.6720011234283447
          ],
          "Parents": []
        },
        {
          "Name": "Baby",
          "Confidence": 97.53484344482422,
          "bbox": [
            0.12484141439199448,
            0.12123048305511475,
            0.4460567831993103,
            0.6720011234283447
          ],
          "Parents": [
            "Person"
          ]
        }
      ]
    },
    {
      "frame": 5,
      "timestamp": 5.0,
      "people": [
        {
          "type": "baby",
          "age": 1,
          "age_range": "0-2",
          "gender": "unknown",
          "emotion": "neutral"
        }
      ],
      "detected_objects": [
        {
          "Name": "Person",
          "Confidence": 99.34605407714844,
          "bbox": [
            0.15056386590003967,
            0.12149716168642044,
            0.41242948174476624,
            0.6536832451820374
          ],
          "Parents": []
        },
        {
          "Name": "Baby",
          "Confidence": 99.34605407714844,
          "bbox": [
            0.15056386590003967,
            0.12149716168642044,
            0.41242948174476624,
            0.6536832451820374
          ],
          "Parents": [
            "Person"
          ]
        }
      ]
    },
    {
      "frame": 6,
      "timestamp": 6.0,
      "people": [
        {
          "type": "baby",
          "age": 1,
          "age_range": "0-2",
          "gender": "unknown",
          "emotion": "neutral"
        }
      ],
      "detected_objects": [
        {
          "Name": "Person",
          "Confidence": 99.47924041748047,
          "bbox": [
            0.14884164929389954,
            0.12088578194379807,
            0.39732101559638977,
            0.6676491498947144
          ],
          "Parents": []
        },
        {
          "Name": "Baby",
          "Confidence": 99.47924041748047,
          "bbox": [
            0.14884164929389954,
            0.12088578194379807,
            0.39732101559638977,
            0.6676491498947144
          ],
          "Parents": [
            "Person"
          ]
        },
        {
          "Name": "Sock",
          "Confidence": 85.92677307128906,
          "bbox": [
            0.1486046016216278,
            0.5672743916511536,
            0.1747453361749649,
            0.22068320214748383
          ],
          "Parents": [
            "Clothing",
            "Hosiery"
          ]
        }
      ]
    },
    {
      "frame": 7,
      "timestamp": 7.0,
      "people": [
        {
          "type": "baby",
          "age": 1,
          "age_range": "0-2",
          "gender": "unknown",
          "emotion": "calm"
        }
      ],
      "detected_objects": [
        {
          "Name": "Person",
          "Confidence": 98.75727844238281,
          "bbox": [
            0.16273857653141022,
            0.12458096444606781,
            0.3975341320037842,
            0.6460108160972595
          ],
          "Parents": []
        },
        {
          "Name": "Baby",
          "Confidence": 98.75727844238281,
          "bbox": [
            0.16273857653141022,
            0.12458096444606781,
            0.3975341320037842,
            0.6460108160972595
          ],
          "Parents": [
            "Person"
          ]
        }
      ]
    },
    {
      "frame": 8,
      "timestamp": 8.0,
      "people": [
        {
          "type": "baby",
          "age": 1,
          "age_range": "0-2",
          "gender": "unknown",
          "emotion": "neutral"
        }
      ],
      "detected_objects": [
        {
          "Name": "Person",
          "Confidence": 98.1954574584961,
          "bbox": [
            0.14023138582706451,
            0.11980287730693817,
            0.43166056275367737,
            0.6569374203681946
          ],
          "Parents": []
        },
        {
          "Name": "Baby",
          "Confidence": 98.1954574584961,
          "bbox": [
            0.14023138582706451,
            0.11980287730693817,
            0.43166056275367737,
            0.6569374203681946
          ],
          "Parents": [
            "Person"
          ]
        }
      ]
    },
    {
      "frame": 9,
      "timestamp": 9.0,
      "people": [
        {
          "type": "baby",
          "age": 1,
          "age_range": "0-2",
          "gender": "unknown",
          "emotion": "calm"
        }
      ],
      "detected_objects": [
        {
          "Name": "Person",
          "Confidence": 99.02836608886719,
          "bbox": [
            0.15559495985507965,
            0.12190592288970947,
            0.4121650755405426,
            0.6641669273376465
          ],
          "Parents": []
        },
        {
          "Name": "Baby",
          "Confidence": 99.02836608886719,
          "bbox": [
            0.15559495985507965,
            0.12190592288970947,
            0.4121650755405426,
            0.6641669273376465
          ],
          "Parents": [
            "Person"
          ]
        }
      ]
    },
    {
      "frame": 10,
      "timestamp": 10.0,
      "people": [
        {
          "type": "baby",
          "age": 1,
          "age_range": "0-2",
          "gender": "unknown",
          "emotion": "neutral"
        }
      ],
      "detected_objects": [
        {
          "Name": "Person",
          "Confidence": 99.10462188720703,
          "bbox": [
            0.14245058596134186,
            0.1250789761543274,
            0.4402755796909332,
            0.6514782905578613
          ],
          "Parents": []
        },
        {
          "Name": "Baby",
          "Confidence": 99.10462188720703,
          "bbox": [
            0.14245058596134186,
            0.1250789761543274,
            0.4402755796909332,
            0.6514782905578613
          ],
          "Parents": [
            "Person"
          ]
        },
        {
          "Name": "Sock",
          "Confidence": 83.32444763183594,
          "bbox": [
            0.1431713104248047,
            0.5464432239532471,
            0.09957506507635117,
            0.1826464831829071
          ],
          "Parents": [
            "Clothing",
            "Hosiery"
          ]
        }
      ]
    },
    {
      "frame": 11,
      "timestamp": 11.0,
      "people": [
        {
          "type": "baby",
          "age": 1,
          "age_range": "0-2",
          "gender": "unknown",
          "emotion": "neutral"
        }
      ],
      "detected_objects": [
        {
          "Name": "Person",
          "Confidence": 93.0784683227539,
          "bbox": [
            0.28389036655426025,
            0.12153871357440948,
            0.2824072241783142,
            0.6494371891021729
          ],
          "Parents": []
        },
        {
          "Name": "Person",
          "Confidence": 88.28419494628906,
          "bbox": [
            0.12790174782276154,
            0.566767692565918,
            0.2562255263328552,
            0.3097671866416931
          ],
          "Parents": []
        },
        {
          "Name": "Baby",
          "Confidence": 93.0784683227539,
          "bbox": [
            0.28389036655426025,
            0.12153871357440948,
            0.2824072241783142,
            0.6494371891021729
          ],
          "Parents": [
            "Person"
          ]
        },
        {
          "Name": "Baby",
          "Confidence": 88.28419494628906,
          "bbox": [
            0.12790174782276154,
            0.566767692565918,
            0.2562255263328552,
            0.3097671866416931
          ],
          "Parents": [
            "Person"
          ]
        }
      ]
    },
    {
      "frame": 12,
      "timestamp": 12.0,
      "people": [
        {
          "type": "baby",
          "age": 1,
          "age_range": "0-2",
          "gender": "unknown",
          "emotion": "neutral"
        }
      ],
      "detected_objects": [
        {
          "Name": "Person",
          "Confidence": 99.59986114501953,
          "bbox": [
            0.14316235482692719,
            0.12272036075592041,
            0.43278926610946655,
            0.6460562944412231
          ],
          "Parents": []
        },
        {
          "Name": "Person",
          "Confidence": 89.20809936523438,
          "bbox": [
            0.12394779920578003,
            0.12589368224143982,
            0.08317135274410248,
            0.4608229696750641
          ],
          "Parents": []
        },
        {
          "Name": "Baby",
          "Confidence": 99.59986114501953,
          "bbox": [
            0.14316235482692719,
            0.12272036075592041,
            0.43278926610946655,
            0.6460562944412231
          ],
          "Parents": [
            "Person"
          ]
        }
      ]
    },
    {
      "frame": 13,
      "timestamp": 13.0,
      "people": [
        {
          "type": "baby",
          "age": 1,
          "age_range": "0-2",
          "gender": "unknown",
          "emotion": "calm"
        }
      ],
      "detected_objects": [
        {
          "Name": "Person",
          "Confidence": 98.56151580810547,
          "bbox": [
            0.1362987607717514,
            0.12318126857280731,
            0.4253388047218323,
            0.6497398018836975
          ],
          "Parents": []
        },
        {
          "Name": "Baby",
          "Confidence": 98.56151580810547,
          "bbox": [
            0.1362987607717514,
            0.12318126857280731,
            0.4253388047218323,
            0.6497398018836975
          ],
          "Parents": [
            "Person"
          ]
        }
      ]
    },
    {
      "frame": 14,
      "timestamp": 14.0,
      "people": [
        {
          "type": "baby",
          "age": 1,
          "age_range": "0-2",
          "gender": "unknown",
          "emotion": "neutral"
        }
      ],
      "detected_objects": [
        {
          "Name": "Person",
          "Confidence": 99.47885131835938,
          "bbox": [
            0.15394939482212067,
            0.12174970656633377,
            0.4172777533531189,
            0.6496782302856445
          ],
          "Parents": []
        },
        {
          "Name": "Baby",
          "Confidence": 99.47885131835938,
          "bbox": [
            0.15394939482212067,
            0.12174970656633377,
            0.4172777533531189,
            0.6496782302856445
          ],
          "Parents": [
            "Person"
          ]
        }
      ]
    },
    {
      "frame": 15,
      "timestamp": 15.0,
      "people": [
        {
          "type": "baby",
          "age": 1,
          "age_range": "0-2",
          "gender": "unknown",
          "emotion": "calm"
        }
      ],
      "detected_objects": [
        {
          "Name": "Person",
          "Confidence": 99.22415161132812,
          "bbox": [
            0.15815117955207825,
            0.12046781182289124,
            0.40478891134262085,
            0.6451333165168762
          ],
          "Parents": []
        },
        {
          "Name": "Baby",
          "Confidence": 99.22415161132812,
          "bbox": [
            0.15815117955207825,
            0.12046781182289124,
            0.40478891134262085,
            0.6451333165168762
          ],
          "Parents": [
            "Person"
          ]
        }
      ]
    },
    {
      "frame": 16,
      "timestamp": 16.0,
      "people": [
        {
          "type": "baby",
          "age": 1,
          "age_range": "0-2",
          "gender": "unknown",
          "emotion": "neutral"
        }
      ],
      "detected_objects": [
        {
          "Name": "Person",
          "Confidence": 98.6617660522461,
          "bbox": [
            0.17663533985614777,
            0.12048439681529999,
            0.39399129152297974,
            0.6379207968711853
          ],
          "Parents": []
        },
        {
          "Name": "Baby",
          "Confidence": 98.6617660522461,
          "bbox": [
            0.17663533985614777,
            0.12048439681529999,
            0.39399129152297974,
            0.6379207968711853
          ],
          "Parents": [
            "Person"
          ]
        }
      ]
    },
    {
      "frame": 17,
      "timestamp": 17.0,
      "people": [
        {
          "type": "baby",
          "age": 1,
          "age_range": "0-2",
          "gender": "unknown",
          "emotion": "calm"
        }
      ],
      "detected_objects": [
        {
          "Name": "Person",
          "Confidence": 96.90922546386719,
          "bbox": [
            0.24159863591194153,
            0.12173004448413849,
            0.3858897089958191,
            0.6312839984893799
          ],
          "Parents": []
        },
        {
          "Name": "Baby",
          "Confidence": 96.90922546386719,
          "bbox": [
            0.24159863591194153,
            0.12173004448413849,
            0.3858897089958191,
            0.6312839984893799
          ],
          "Parents": [
            "Person"
          ]
        }
      ]
    },
    {
      "frame": 18,
      "timestamp": 18.0,
      "people": [
        {
          "type": "baby",
          "age": 1,
          "age_range": "0-2",
          "gender": "unknown",
          "emotion": "neutral"
        }
      ],
      "detected_objects": [
        {
          "Name": "Person",
          "Confidence": 99.08382415771484,
          "bbox": [
            0.1641543209552765,
            0.1227058544754982,
            0.39827460050582886,
            0.6639867424964905
          ],
          "Parents": []
        },
        {
          "Name": "Baby",
          "Confidence": 99.08382415771484,
          "bbox": [
            0.1641543209552765,
            0.1227058544754982,
            0.39827460050582886,
            0.6639867424964905
          ],
          "Parents": [
            "Person"
          ]
        }
      ]
    },
    {
      "frame": 19,
      "timestamp": 19.0,
      "people": [
        {
          "type": "baby",
          "age": 1,
          "age_range": "0-2",
          "gender": "unknown",
          "emotion": "calm"
        }
      ],
      "detected_objects": [
        {
          "Name": "Person",
          "Confidence": 96.03546905517578,
          "bbox": [
            0.17181751132011414,
            0.12454966455698013,
            0.39232879877090454,
            0.6504762172698975
          ],
          "Parents": []
        },
        {
          "Name": "Baby",
          "Confidence": 96.03546905517578,
          "bbox": [
            0.17181751132011414,
            0.12454966455698013,
            0.39232879877090454,
            0.6504762172698975
          ],
          "Parents": [
            "Person"
          ]
        },
        {
          "Name": "Package",
          "Confidence": 85.37479400634766,
          "bbox": [
            0.3052158057689667,
            0.6934400200843811,
            0.09481623023748398,
            0.18300849199295044
          ],
          "Parents": [
            "Box"
          ]
        }
      ]
    }
  ]
}